aurora/__init__.py
aurora/cli.py
aurora/date_helpers.py
aurora/graph.py
aurora/templates/index.html
aurora_ssg-0.1.7.dist-info/LICENSE
aurora_ssg-0.1.7.dist-info/METADATA
aurora_ssg-0.1.7.dist-info/WHEEL
aurora_ssg-0.1.7.dist-info/entry_points.txt
aurora_ssg-0.1.7.dist-info/top_level.txt
aurora_ssg-0.1.7.dist-info/RECORD
