Metadata-Version: 2.1
Name: aurora-ssg
Version: 0.1.7
Summary: A fast static site generator implemented in Python.
Home-page: https://github.com/capjamesg/aurora
Author: capjamesg
Author-email: readers@jamesg.blog
Classifier: Programming Language :: Python :: 3
Classifier: License :: OSI Approved :: MIT License
Classifier: Operating System :: OS Independent
Requires-Python: >=3.7
License-File: LICENSE
Requires-Dist: jinja2
Requires-Dist: livereload
Requires-Dist: toposort
Requires-Dist: pyromark~=0.6.0
Requires-Dist: python-frontmatter
Requires-Dist: requests
Requires-Dist: progress
Requires-Dist: click
Requires-Dist: orjson
Requires-Dist: tqdm
Requires-Dist: python-dateutil
Requires-Dist: chardet
Provides-Extra: dev
Requires-Dist: flake8; extra == "dev"
Requires-Dist: black==24.10.0; extra == "dev"
Requires-Dist: isort; extra == "dev"
Requires-Dist: twine; extra == "dev"
Requires-Dist: pytest; extra == "dev"
Requires-Dist: wheel; extra == "dev"
Requires-Dist: mkdocs-material; extra == "dev"
Requires-Dist: mkdocs; extra == "dev"
